rs_file_reader/__init__.py
rs_file_reader/__main__.py
rs_file_reader/gui_plot.json
rs_file_reader/rs_analysis.py
rs_file_reader/rs_file.py
rs_file_reader/rs_plot_gui.py
rs_file_reader/tool_box.py
rs_file_reader-0.2.9.dist-info/METADATA
rs_file_reader-0.2.9.dist-info/WHEEL
rs_file_reader-0.2.9.dist-info/licenses/LICENSE
rs_file_reader-0.2.9.dist-info/RECORD
