Metadata-Version: 2.4
Name: rs_file_reader
Version: 0.2.9
Summary: Utility for reading Rhode and Schwarz oscilloscope binary files
Project-URL: Homepage, https://github.com/simonwaid/rs_file_reader
Project-URL: Bug Tracker, https://github.com/simonwaid/rs_file_reader/issues
Author-email: Simon Waid <simon.waid@oeaw.ac.at>
License:                    GNU LESSER GENERAL PUBLIC LICENSE
License-File: LICENSE
Classifier: License :: OSI Approved :: GNU Lesser General Public License v3 (LGPLv3)
Classifier: Operating System :: OS Independent
Classifier: Programming Language :: Python :: 3
Requires-Python: >=3.8
Requires-Dist: matplotlib>=3.5.0
Requires-Dist: numba>=0.53.1
Requires-Dist: numpy>=1.20.3
Requires-Dist: pandas>=1.3.4
Requires-Dist: pyside6>=6.3.1
Requires-Dist: scipy>=1.7.3
